{
	"required": true,
	"minVersion": "0.8",
	"package": "dev.beast.mods.shimmer.core.mixin",
	"compatibilityLevel": "JAVA_21",
	"mixins": ["BarrierBlockMixin", "EntityMixin", "ItemMixin", "LevelMixin", "LivingEntityMixin", "MinecraftServerMixin", "MobMixin", "PlayerMixin", "ServerLevelMixin", "ServerPlayerMixin"],
	"client": ["AbstractClientPlayerMixin", "CameraMixin", "ClientLevelMixin", "ClientPacketListenerMixin", "GameRendererMixin", "KeyMappingMixin", "LevelRendererMixin", "LocalPlayerMixin", "MinecraftClientMixin", "MouseHandlerMixin", "ScreenMixin"],
	"injectors": {
		"defaultRequire": 1,
		"maxShiftBy": 2
	}
}